inmanage.py
ieisystem_inmanage_sdk/__init__.py
ieisystem_inmanage_sdk/command/IpmiFunc.py
ieisystem_inmanage_sdk/command/RedfishFunc.py
ieisystem_inmanage_sdk/command/RestFunc.py
ieisystem_inmanage_sdk/command/__init__.py
ieisystem_inmanage_sdk/command/backup.py
ieisystem_inmanage_sdk/command/restore.py
ieisystem_inmanage_sdk/command/M5Log/__init__.py
ieisystem_inmanage_sdk/command/M5Log/biosPostEventStr.py
ieisystem_inmanage_sdk/command/M5Log/commonInfoStr.py
ieisystem_inmanage_sdk/command/M5Log/eventLogString.py
ieisystem_inmanage_sdk/command/M5Log/sensorEventStr.py
ieisystem_inmanage_sdk/command/M5Log/sensorSpecificEventStr.py
ieisystem_inmanage_sdk/command/M5Log/showSensorDesc.py
ieisystem_inmanage_sdk/command/bios/A7.xml
ieisystem_inmanage_sdk/command/bios/M4.xml
ieisystem_inmanage_sdk/command/bios/M5.xml
ieisystem_inmanage_sdk/command/bios/M6-N.xml
ieisystem_inmanage_sdk/command/bios/M6.xml
ieisystem_inmanage_sdk/command/bios/M7.xml
ieisystem_inmanage_sdk/command/bios/NF3180A6.xml
ieisystem_inmanage_sdk/command/bios/NF3280A6.xml
ieisystem_inmanage_sdk/command/bios/NF5180M5.xml
ieisystem_inmanage_sdk/command/bios/NF5280M5.xml
ieisystem_inmanage_sdk/command/bios/NF5468A5.xml
ieisystem_inmanage_sdk/command/bios/NF5488A5.xml
ieisystem_inmanage_sdk/command/bios/SA5112M5.xml
ieisystem_inmanage_sdk/command/bios/SA5212M5.xml
ieisystem_inmanage_sdk/conf/NF5180M5.yml
ieisystem_inmanage_sdk/conf/NF5280M5.yml
ieisystem_inmanage_sdk/conf/SA5112M5.yml
ieisystem_inmanage_sdk/conf/SA5212M5.yml
ieisystem_inmanage_sdk/conf/__init__.py
ieisystem_inmanage_sdk/interface/Base.py
ieisystem_inmanage_sdk/interface/CommonA5.py
ieisystem_inmanage_sdk/interface/CommonA6.py
ieisystem_inmanage_sdk/interface/CommonA7.py
ieisystem_inmanage_sdk/interface/CommonA7_11308.py
ieisystem_inmanage_sdk/interface/CommonM5.py
ieisystem_inmanage_sdk/interface/CommonM6.py
ieisystem_inmanage_sdk/interface/CommonM6_41401.py
ieisystem_inmanage_sdk/interface/CommonM6_4140a.py
ieisystemInManage-1.0.0.dist-info/LICENSE
ieisystemInManage-1.0.0.dist-info/METADATA
ieisystemInManage-1.0.0.dist-info/WHEEL
ieisystemInManage-1.0.0.dist-info/top_level.txt
ieisystemInManage-1.0.0.dist-info/RECORD
